odoo/addons/analytic_distribution_widget_remove_save/README.rst
odoo/addons/analytic_distribution_widget_remove_save/__init__.py
odoo/addons/analytic_distribution_widget_remove_save/__manifest__.py
odoo/addons/analytic_distribution_widget_remove_save/i18n/analytic_distribution_widget_remove_save.pot
odoo/addons/analytic_distribution_widget_remove_save/i18n/ca.po
odoo/addons/analytic_distribution_widget_remove_save/i18n/eu_ES.po
odoo/addons/analytic_distribution_widget_remove_save/i18n/it.po
odoo/addons/analytic_distribution_widget_remove_save/readme/CONTEXT.md
odoo/addons/analytic_distribution_widget_remove_save/readme/CONTRIBUTORS.md
odoo/addons/analytic_distribution_widget_remove_save/readme/DESCRIPTION.md
odoo/addons/analytic_distribution_widget_remove_save/readme/INSTALL.md
odoo/addons/analytic_distribution_widget_remove_save/readme/USAGE.md
odoo/addons/analytic_distribution_widget_remove_save/static/description/icon.png
odoo/addons/analytic_distribution_widget_remove_save/static/description/index.html
odoo/addons/analytic_distribution_widget_remove_save/static/description/widget_analytic_screenshot.png
odoo/addons/analytic_distribution_widget_remove_save/static/src/xml/analytic_distribution.xml
odoo_addon_analytic_distribution_widget_remove_save-16.0.1.0.1.3.dist-info/METADATA
odoo_addon_analytic_distribution_widget_remove_save-16.0.1.0.1.3.dist-info/WHEEL
odoo_addon_analytic_distribution_widget_remove_save-16.0.1.0.1.3.dist-info/top_level.txt
odoo_addon_analytic_distribution_widget_remove_save-16.0.1.0.1.3.dist-info/RECORD
