Metadata-Version: 2.1
Name: odoo-addon-analytic_distribution_widget_remove_save
Version: 16.0.1.0.1.3
Summary: Remove save button on analytic distribution widget
Home-page: https://github.com/OCA/account-analytic
Author: ACSONE SA/NV,Odoo Community Association (OCA)
Author-email: support@odoo-community.org
License: AGPL-3
Classifier: Programming Language :: Python
Classifier: Framework :: Odoo
Classifier: Framework :: Odoo :: 16.0
Classifier: License :: OSI Approved :: GNU Affero General Public License v3
Requires-Python: >=3.10
Requires-Dist: odoo<16.1dev,>=16.0a
